sfp/__init__.py
sfp/sfp.py
sfp-2.1.2.dist-info/LICENSE
sfp-2.1.2.dist-info/METADATA
sfp-2.1.2.dist-info/WHEEL
sfp-2.1.2.dist-info/top_level.txt
sfp-2.1.2.dist-info/RECORD
