Metadata-Version: 2.1
Name: sfp
Version: 2.1.2
Summary: Python implementation of SFP
Home-page: https://github.com/xenocorn/PySFP
Author: XenoCorn
License: UNKNOWN
Platform: UNKNOWN
Classifier: Development Status :: 5 - Production/Stable
Classifier: License :: OSI Approved :: BSD License
Classifier: Topic :: Internet
License-File: LICENSE
Requires-Dist: rfc3986 (==1.5.0)
